{
  "stats": {
    "expected": 15,
    "unexpected": 3,
    "skipped": 0,
    "flaky": 0,
    "duration": 9521
  },
  "tests": [
    {
      "title": ".wrapper-centered genişliği mobile göre ayarlanmış mı?",
      "status": "passed",
      "duration": 586
    },
    {
      "title": "Header öğesinin flex yönüne göre hizası mobile uygun ayarlanmış mı?",
      "status": "passed",
      "duration": 590
    },
    {
      "title": "Header öğeler arası gap mobile uygun ayarlanmış mı?",
      "status": "passed",
      "duration": 109
    },
    {
      "title": "Header öğesinin flex yönünün dik eksenine göre hizası mobile uygun ayarlanmış mı?",
      "status": "passed",
      "duration": 117
    },
    {
      "title": "Viewport meta etiketi doğru ayarlanmış mı?",
      "status": "failed",
      "duration": 498
    },
    {
      "title": "Header öğesinin padding değerleri mobile uygun ayarlanmış mı?",
      "status": "passed",
      "duration": 846
    },
    {
      "title": "Header öğesinin flex yönü mobile uygun ayarlanmış mı?",
      "status": "passed",
      "duration": 99
    },
    {
      "title": ".hero öğesinin üstündeki boşluk mobile uygun ayarlanmış mı?",
      "status": "passed",
      "duration": 1018
    },
    {
      "title": ".hero öğesinin iç boşluğu mobile uygun ayarlanmış mı?",
      "status": "passed",
      "duration": 91
    },
    {
      "title": ".hero öğesinin köşe yuvarlaklığı mobile uygun ayarlanmış mı?",
      "status": "passed",
      "duration": 999
    },
    {
      "title": "Nav linkleri yazı hizası mobil tasarıma uygun mu?",
      "status": "passed",
      "duration": 1274
    },
    {
      "title": ".hero öğesinin flex yönüne göre hizası mobile uygun ayarlanmış mı?",
      "status": "passed",
      "duration": 118
    },
    {
      "title": ".hero öğesinin yüksekliği mobile uygun ayarlanmış mı?",
      "status": "passed",
      "duration": 96
    },
    {
      "title": "Ana başlık font boyutu doküman font boyutuna endekslenmiş mi?",
      "status": "failed",
      "duration": 1320
    },
    {
      "title": ".hero öğesinin flex yönünün dik eksenine göre hizası mobile uygun ayarlanmış mı?",
      "status": "passed",
      "duration": 1054
    },
    {
      "title": "Nav linklerinin genişlikleri mobile uygun ayarlanmış mı?",
      "status": "passed",
      "duration": 113
    },
    {
      "title": "Doküman yazı boyutu mobile göre ayarlanmış mı?",
      "status": "passed",
      "duration": 314
    },
    {
      "title": "Menü font boyutu doküman font boyutuna endekslenmiş mi?",
      "status": "failed",
      "duration": 280
    }
  ]
}